PatrowlEnginesUtils/PatrowlEngine.py
PatrowlEnginesUtils/PatrowlEngineExceptions.py
PatrowlEnginesUtils/PatrowlEngineTest.py
PatrowlEnginesUtils/__init__.py
PatrowlEnginesUtils-1.2.2.dist-info/LICENSE
PatrowlEnginesUtils-1.2.2.dist-info/METADATA
PatrowlEnginesUtils-1.2.2.dist-info/WHEEL
PatrowlEnginesUtils-1.2.2.dist-info/top_level.txt
PatrowlEnginesUtils-1.2.2.dist-info/RECORD
